README.md
setup.cfg
setup.py
src/__init__.py
src/callbacks.py
src/constraints.py
src/datasets.py
src/initializers.py
src/metrics.py
src/regularizers.py
src/samplers.py
src/utils.py
src/version.py
src/functions/__init__.py
src/functions/affine.py
src/modules/__init__.py
src/modules/_utils.py
src/modules/module_trainer.py
src/modules_usingGpu/__init__.py
src/modules_usingGpu/_utils.py
src/modules_usingGpu/module_trainer_gpu.py
src/transforms/__init__.py
src/transforms/affine_transforms.py
src/transforms/distortion_transforms.py
src/transforms/image_transforms.py
src/transforms/tensor_transforms.py
trainingtorchsample.egg-info/PKG-INFO
trainingtorchsample.egg-info/SOURCES.txt
trainingtorchsample.egg-info/dependency_links.txt
trainingtorchsample.egg-info/top_level.txt