Metadata-Version: 2.1
Name: trainingtorchsample
Version: 0.1.3
Summary: High-Level Training, Augmentation, and Sampling for Pytorch
Author: NC Cullen
Author-email: nickmarch31@yahoo.com
License: UNKNOWN
Platform: UNKNOWN
